mciam/__init__.py
mciam/main.py
mciam/command/__init__.py
mciam/command/run.py
mciam/huawei/__init__.py
mciam/huawei/iam.py
mciam/huawei/listuser.py
mciam/huawei/userpocliy.py
mciam-0.2.dist-info/METADATA
mciam-0.2.dist-info/WHEEL
mciam-0.2.dist-info/entry_points.txt
mciam-0.2.dist-info/top_level.txt
mciam-0.2.dist-info/RECORD
