Metadata-Version: 2.1
Name: mciam
Version: 0.2
Requires-Dist: click
Requires-Dist: tabulate
Requires-Dist: wcwidth
